hdf5vault/check.py
hdf5vault/common.py
hdf5vault/create.py
hdf5vault/hdf5_archive_info.py
hdf5vault/unpack.py
hdf5vault-0.3.2.dist-info/METADATA
hdf5vault-0.3.2.dist-info/WHEEL
hdf5vault-0.3.2.dist-info/entry_points.txt
hdf5vault-0.3.2.dist-info/licenses/LICENSE
hdf5vault-0.3.2.dist-info/RECORD
