Metadata-Version: 2.4
Name: hdf5vault
Version: 0.3.2
Summary: A parallel HDF5-based archiving tool.
Author-email: Daniel Roten <daniel.roten@fmi.ch>
License: MIT
License-File: LICENSE
Requires-Python: >=3.8
Requires-Dist: blosc2
Requires-Dist: h5py
Requires-Dist: humanize
Requires-Dist: mpi4py
Requires-Dist: pandas
